{
  "username": "adhitShet",
  "avatarUrl": "https://avatars.githubusercontent.com/u/131381638?v=4",
  "githubUrl": "https://github.com/adhitShet",
  "score": {
    "score": 55.77,
    "prScore": 55.77,
    "issueScore": 0,
    "reviewScore": 0,
    "commentScore": 0
  },
  "tier": "regular",
  "characterClass": "Builder",
  "stats": {
    "commits": 5,
    "prs": 0,
    "prsMerged": 0,
    "prAdditions": 0,
    "prDeletions": 0,
    "prChangedFiles": 0,
    "prMergeRate": 0,
    "issues": 0,
    "issuesClosed": 0,
    "reviews": 0,
    "reviewsApproved": 0,
    "reviewsChangesRequested": 0,
    "comments": 0,
    "commitAdditions": 198,
    "commitDeletions": 22,
    "commitChangedFiles": 19
  },
  "period": {
    "weekly": {
      "prs": 0,
      "issues": 0,
      "reviews": 0,
      "comments": 0,
      "commitAdditions": 0,
      "commitDeletions": 0,
      "commits": 0
    },
    "monthly": {
      "prs": 0,
      "issues": 0,
      "reviews": 0,
      "comments": 0,
      "commitAdditions": 198,
      "commitDeletions": 22,
      "commits": 5
    }
  },
  "firstContribution": null,
  "lastContribution": null,
  "recentPRs": [],
  "recentIssues": [],
  "recentReviews": [],
  "recentActivityDays": {},
  "skills": [
    "Direct Commits"
  ],
  "achievements": [],
  "recentCommitDays": {
    "2026-02-20": 5
  }
}