{
  "username": "cryst-hq",
  "avatarUrl": "https://avatars.githubusercontent.com/u/230207759?u=bb9b65bac0ab18be7fccf58b5cea150f95ded3bc&v=4",
  "githubUrl": "https://github.com/cryst-hq",
  "score": {
    "score": 27.1,
    "prScore": 27.1,
    "issueScore": 0,
    "reviewScore": 0,
    "commentScore": 0
  },
  "tier": "beginner",
  "characterClass": "Builder",
  "stats": {
    "commits": 0,
    "prs": 2,
    "prsMerged": 0,
    "prAdditions": 213,
    "prDeletions": 21,
    "prChangedFiles": 8,
    "prMergeRate": 0,
    "issues": 0,
    "issuesClosed": 0,
    "reviews": 0,
    "reviewsApproved": 0,
    "reviewsChangesRequested": 0,
    "comments": 0,
    "commitAdditions": 0,
    "commitDeletions": 0,
    "commitChangedFiles": 0
  },
  "period": {
    "weekly": {
      "prs": 2,
      "issues": 0,
      "reviews": 0,
      "comments": 0,
      "commitAdditions": 0,
      "commitDeletions": 0,
      "commits": 0
    },
    "monthly": {
      "prs": 2,
      "issues": 0,
      "reviews": 0,
      "comments": 0,
      "commitAdditions": 0,
      "commitDeletions": 0,
      "commits": 0
    }
  },
  "firstContribution": "2026-03-09T20:20:29Z",
  "lastContribution": "2026-03-09T20:57:53Z",
  "recentPRs": [
    {
      "number": 41434,
      "title": "Bootstrap unloaded launchd gateway on restart",
      "state": "OPEN",
      "merged": false,
      "createdAt": "2026-03-09T20:57:53Z",
      "mergedAt": null,
      "additions": 80,
      "deletions": 10,
      "changedFiles": 4
    },
    {
      "number": 41408,
      "title": "Retry LanceDB initialization after failures",
      "state": "OPEN",
      "merged": false,
      "createdAt": "2026-03-09T20:20:29Z",
      "mergedAt": null,
      "additions": 133,
      "deletions": 11,
      "changedFiles": 4
    }
  ],
  "recentIssues": [],
  "recentReviews": [],
  "recentActivityDays": {
    "2026-03-09": {
      "prs": 2,
      "issues": 0,
      "reviews": 0
    }
  },
  "skills": [
    "Pull Requests"
  ],
  "achievements": [],
  "recentCommitDays": {}
}