{
  "username": "dennisvanderpool",
  "avatarUrl": "https://avatars.githubusercontent.com/u/24899089?u=2ab6be971c81de6c0b4101064301f4f838470e8a&v=4",
  "githubUrl": "https://github.com/dennisvanderpool",
  "score": {
    "score": 13.5,
    "prScore": 0,
    "issueScore": 8,
    "reviewScore": 4,
    "commentScore": 1.5
  },
  "tier": "beginner",
  "characterClass": "Contributor",
  "stats": {
    "commits": 0,
    "prs": 0,
    "prsMerged": 0,
    "prAdditions": 0,
    "prDeletions": 0,
    "prChangedFiles": 0,
    "prMergeRate": 0,
    "issues": 1,
    "issuesClosed": 1,
    "reviews": 1,
    "reviewsApproved": 1,
    "reviewsChangesRequested": 0,
    "comments": 3,
    "commitAdditions": 0,
    "commitDeletions": 0,
    "weeklyCommits": 0,
    "monthlyCommits": 0,
    "commitChangedFiles": 0
  },
  "period": {
    "weekly": {
      "prs": 0,
      "issues": 0,
      "reviews": 0,
      "comments": 0,
      "commitAdditions": 0,
      "commitDeletions": 0,
      "commits": 0
    },
    "monthly": {
      "prs": 0,
      "issues": 1,
      "reviews": 1,
      "comments": 3,
      "commitAdditions": 0,
      "commitDeletions": 0,
      "commits": 0
    }
  },
  "firstContribution": "2026-03-02T20:51:40Z",
  "lastContribution": "2026-03-04T19:53:00Z",
  "recentPRs": [],
  "recentIssues": [
    {
      "number": 32164,
      "title": "[Bug]: OpenClaw Config Raw redacts way too much and can't save file",
      "state": "CLOSED",
      "createdAt": "2026-03-02T20:51:40Z",
      "closedAt": "2026-03-02T22:14:36Z"
    }
  ],
  "recentReviews": [
    {
      "prNumber": 34542,
      "state": "APPROVED",
      "createdAt": "2026-03-04T19:53:00Z"
    }
  ],
  "skills": [
    "Code Review",
    "Issue Reporting",
    "Discussion"
  ],
  "achievements": [],
  "recentCommitDays": {},
  "recentActivityDays": {
    "2026-03-02": {
      "prs": 0,
      "issues": 1,
      "reviews": 0
    },
    "2026-03-04": {
      "prs": 0,
      "issues": 0,
      "reviews": 1
    }
  }
}