{
  "username": "du2852625",
  "avatarUrl": "https://avatars.githubusercontent.com/u/22150294?u=0020e7a2f97a74168c7a2c57a3591a4ba11b661b&v=4",
  "githubUrl": "https://github.com/du2852625",
  "score": {
    "score": 7,
    "prScore": 7,
    "issueScore": 0,
    "reviewScore": 0,
    "commentScore": 0
  },
  "tier": "beginner",
  "characterClass": "Builder",
  "stats": {
    "commits": 0,
    "prs": 1,
    "prsMerged": 0,
    "prAdditions": 0,
    "prDeletions": 0,
    "prChangedFiles": 0,
    "prMergeRate": 0,
    "issues": 0,
    "issuesClosed": 0,
    "reviews": 0,
    "reviewsApproved": 0,
    "reviewsChangesRequested": 0,
    "comments": 0,
    "commitAdditions": 0,
    "commitDeletions": 0,
    "commitChangedFiles": 0
  },
  "period": {
    "weekly": {
      "prs": 1,
      "issues": 0,
      "reviews": 0,
      "comments": 0,
      "commitAdditions": 0,
      "commitDeletions": 0,
      "commits": 0
    },
    "monthly": {
      "prs": 1,
      "issues": 0,
      "reviews": 0,
      "comments": 0,
      "commitAdditions": 0,
      "commitDeletions": 0,
      "commits": 0
    }
  },
  "firstContribution": "2026-03-11T21:09:53Z",
  "lastContribution": "2026-03-11T21:09:53Z",
  "recentPRs": [
    {
      "number": 43472,
      "title": "Merge pull request #1 from openclaw/main 同步",
      "state": "OPEN",
      "merged": false,
      "createdAt": "2026-03-11T21:09:53Z",
      "mergedAt": null,
      "additions": 0,
      "deletions": 0,
      "changedFiles": 0
    }
  ],
  "recentIssues": [],
  "recentReviews": [],
  "recentActivityDays": {
    "2026-03-11": {
      "prs": 1,
      "issues": 0,
      "reviews": 0
    }
  },
  "skills": [
    "Pull Requests"
  ],
  "achievements": [],
  "recentCommitDays": {}
}