{
  "username": "jsirish",
  "avatarUrl": "https://avatars.githubusercontent.com/u/1163643?u=b6df57bc2a0e8429b9e079219ab94ea0019c89b4&v=4",
  "githubUrl": "https://github.com/jsirish",
  "score": {
    "score": 15.68,
    "prScore": 9.18,
    "issueScore": 0,
    "reviewScore": 6,
    "commentScore": 0.5
  },
  "tier": "beginner",
  "characterClass": "Reviewer",
  "stats": {
    "commits": 0,
    "prs": 1,
    "prsMerged": 0,
    "prAdditions": 35,
    "prDeletions": 2,
    "prChangedFiles": 2,
    "prMergeRate": 0,
    "issues": 0,
    "issuesClosed": 0,
    "reviews": 2,
    "reviewsApproved": 0,
    "reviewsChangesRequested": 0,
    "comments": 1,
    "commitAdditions": 0,
    "commitDeletions": 0,
    "weeklyCommits": 0,
    "monthlyCommits": 0,
    "commitChangedFiles": 0
  },
  "period": {
    "weekly": {
      "prs": 1,
      "issues": 0,
      "reviews": 2,
      "comments": 1,
      "commitAdditions": 0,
      "commitDeletions": 0,
      "commits": 0
    },
    "monthly": {
      "prs": 1,
      "issues": 0,
      "reviews": 2,
      "comments": 1,
      "commitAdditions": 0,
      "commitDeletions": 0,
      "commits": 0
    }
  },
  "firstContribution": "2026-03-11T18:36:07Z",
  "lastContribution": "2026-03-11T19:01:04Z",
  "recentPRs": [
    {
      "number": 43407,
      "title": "fix(agents): suppress missing tool warning for known core tools",
      "state": "CLOSED",
      "merged": false,
      "createdAt": "2026-03-11T18:36:07Z",
      "mergedAt": null,
      "additions": 35,
      "deletions": 2,
      "changedFiles": 2
    }
  ],
  "recentIssues": [],
  "recentReviews": [
    {
      "prNumber": 43407,
      "state": "COMMENTED",
      "createdAt": "2026-03-11T18:56:03Z"
    },
    {
      "prNumber": 43407,
      "state": "COMMENTED",
      "createdAt": "2026-03-11T18:56:02Z"
    }
  ],
  "skills": [
    "Pull Requests",
    "Code Review",
    "Discussion"
  ],
  "achievements": [],
  "recentCommitDays": {},
  "recentActivityDays": {
    "2026-03-11": {
      "prs": 1,
      "issues": 0,
      "reviews": 2
    }
  }
}