{
  "username": "lnO4X",
  "avatarUrl": "https://avatars.githubusercontent.com/u/6882017?u=e4d050e5772d8232c05fb0d3ff35768f746b5678&v=4",
  "githubUrl": "https://github.com/lnO4X",
  "score": {
    "score": 11.1,
    "prScore": 10.6,
    "issueScore": 0,
    "reviewScore": 0,
    "commentScore": 0.5
  },
  "tier": "beginner",
  "characterClass": "Builder",
  "stats": {
    "commits": 0,
    "prs": 1,
    "prsMerged": 0,
    "prAdditions": 363,
    "prDeletions": 38,
    "prChangedFiles": 2,
    "prMergeRate": 0,
    "issues": 0,
    "issuesClosed": 0,
    "reviews": 0,
    "reviewsApproved": 0,
    "reviewsChangesRequested": 0,
    "comments": 1,
    "commitAdditions": 0,
    "commitDeletions": 0,
    "commitChangedFiles": 0
  },
  "period": {
    "weekly": {
      "prs": 1,
      "issues": 0,
      "reviews": 0,
      "comments": 1,
      "commitAdditions": 0,
      "commitDeletions": 0,
      "commits": 0
    },
    "monthly": {
      "prs": 1,
      "issues": 0,
      "reviews": 0,
      "comments": 1,
      "commitAdditions": 0,
      "commitDeletions": 0,
      "commits": 0
    }
  },
  "firstContribution": "2026-03-10T02:24:38Z",
  "lastContribution": "2026-03-10T10:25:03Z",
  "recentPRs": [
    {
      "number": 41637,
      "title": "fix(feishu): share webhook server across accounts on same host:port",
      "state": "OPEN",
      "merged": false,
      "createdAt": "2026-03-10T02:24:38Z",
      "mergedAt": null,
      "additions": 363,
      "deletions": 38,
      "changedFiles": 2
    }
  ],
  "recentIssues": [],
  "recentReviews": [],
  "recentActivityDays": {
    "2026-03-10": {
      "prs": 1,
      "issues": 0,
      "reviews": 0
    }
  },
  "skills": [
    "Pull Requests",
    "Discussion"
  ],
  "achievements": [],
  "recentCommitDays": {}
}