{
  "username": "pomelo-nwu",
  "avatarUrl": "https://avatars.githubusercontent.com/u/10703060?u=357d9e781c1dbc88b494a6425fc1536250d99883&v=4",
  "githubUrl": "https://github.com/pomelo-nwu",
  "score": {
    "score": 104.33,
    "prScore": 103.33,
    "issueScore": 0,
    "reviewScore": 0,
    "commentScore": 1
  },
  "tier": "regular",
  "characterClass": "Contributor",
  "stats": {
    "commits": 0,
    "prs": 1,
    "prsMerged": 1,
    "prAdditions": 532,
    "prDeletions": 1,
    "prChangedFiles": 21,
    "prMergeRate": 100,
    "issues": 0,
    "issuesClosed": 0,
    "reviews": 0,
    "reviewsApproved": 0,
    "reviewsChangesRequested": 0,
    "comments": 2,
    "commitAdditions": 503,
    "commitDeletions": 140,
    "weeklyCommits": 0,
    "monthlyCommits": 0,
    "commitChangedFiles": 23
  },
  "period": {
    "weekly": {
      "prs": 1,
      "issues": 0,
      "reviews": 0,
      "comments": 2,
      "commitAdditions": 503,
      "commitDeletions": 140,
      "commits": 2
    },
    "monthly": {
      "prs": 1,
      "issues": 0,
      "reviews": 0,
      "comments": 2,
      "commitAdditions": 503,
      "commitDeletions": 140,
      "commits": 2
    }
  },
  "firstContribution": "2026-03-09T05:27:35Z",
  "lastContribution": "2026-03-10T11:58:46Z",
  "recentPRs": [
    {
      "number": 40634,
      "title": "feat: integrate Alibaba Cloud Model Studio Coding Plan into onboarding wizard",
      "state": "MERGED",
      "merged": true,
      "createdAt": "2026-03-09T05:27:35Z",
      "mergedAt": "2026-03-10T19:58:44Z",
      "additions": 532,
      "deletions": 1,
      "changedFiles": 21
    }
  ],
  "recentIssues": [],
  "recentReviews": [],
  "skills": [
    "Pull Requests",
    "Discussion"
  ],
  "achievements": [],
  "recentCommitDays": {
    "2026-03-10": 2
  },
  "recentActivityDays": {
    "2026-03-09": {
      "prs": 1,
      "issues": 0,
      "reviews": 0
    }
  }
}